README.md
setup.py
anm/__about__.py
anm/__init__.py
anm/anm.py
anm.egg-info/PKG-INFO
anm.egg-info/SOURCES.txt
anm.egg-info/dependency_links.txt
anm.egg-info/requires.txt
anm.egg-info/top_level.txt