Metadata-Version: 1.0
Name: anm
Version: 0.1.1
Summary: ['__summary__']
Home-page: UNKNOWN
Author: Richard Strnad
Author-email: richard@strnad.ch
License: UNKNOWN
Platform: UNKNOWN
